fragment
setup.py
Agora_Fragment.egg-info/PKG-INFO
Agora_Fragment.egg-info/SOURCES.txt
Agora_Fragment.egg-info/dependency_links.txt
Agora_Fragment.egg-info/namespace_packages.txt
Agora_Fragment.egg-info/requires.txt
Agora_Fragment.egg-info/top_level.txt
agora/__init__.py
agora/fragment/__init__.py
agora/fragment/api.py
agora/fragment/server/__init__.py
agora/fragment/server/config.py