Metadata-Version: 1.0
Name: Agora-Fragment
Version: 0.0.1
Summary: An Agora service that collects fragments for graph patterns
Home-page: https://github.com/smartdeveloperhub/agora-fragment
Author: Fernando Serena
Author-email: fernando.serena@centeropenmiddleware.com
License: Apache 2
Keywords: agora,linked-data,search-plan,fragment
Platform: UNKNOWN
